{
  "day": 206,
  "topic": "Verhaltensökonomie",
  "words": [
    {
      "de": "die Verhaltensökonomie",
      "en": "behavioral economics",
      "artikel": "die",
      "example": "Verhaltensökonomie untersucht irrationales Kaufverhalten."
    },
    {
      "de": "die Verlustaversion (Ökonomie)",
      "en": "loss aversion (economics)",
      "artikel": "die",
      "example": "Verlustaversion beeinflusst finanzielle Entscheidungen stark."
    },
    {
      "de": "der Ankereffekt",
      "en": "anchoring effect",
      "artikel": "der",
      "example": "Der Ankereffekt beeinflusst Preisverhandlungen."
    },
    {
      "de": "die Nudge-Theorie",
      "en": "nudge theory",
      "artikel": "die",
      "example": "Die Nudge-Theorie lenkt Verhalten sanft."
    },
    {
      "de": "das irrationale Verhalten",
      "en": "irrational behavior",
      "example": "Irrationales Verhalten widerspricht klassischen Wirtschaftsmodellen."
    },
    {
      "de": "die Entscheidungsheuristik",
      "en": "decision heuristic",
      "artikel": "die",
      "example": "Menschen nutzen oft einfache Entscheidungsheuristiken."
    },
    {
      "de": "die Selbstkontrolle (Ökonomie)",
      "en": "self-control (economics)",
      "artikel": "die",
      "example": "Selbstkontrolle beeinflusst das Sparverhalten."
    },
    {
      "de": "das Herdenverhalten",
      "en": "herd behavior",
      "artikel": "das",
      "example": "Herdenverhalten erklärt viele Börsenbewegungen."
    },
    {
      "de": "die kognitive Verzerrung (Ökonomie)",
      "en": "cognitive bias (economics)",
      "artikel": "die",
      "example": "Kognitive Verzerrungen beeinflussen Investitionsentscheidungen."
    },
    {
      "de": "die Zeitpräferenz",
      "en": "time preference",
      "artikel": "die",
      "example": "Menschen haben oft eine hohe Zeitpräferenz für Gegenwärtiges."
    },
    {
      "de": "die Verhaltensanreize setzen",
      "en": "to set behavioral incentives",
      "example": "Der Staat setzt Verhaltensanreize durch Steuervorteile."
    },
    {
      "de": "die Standardoption",
      "en": "default option",
      "artikel": "die",
      "example": "Die Standardoption beeinflusst die meisten Entscheidungen."
    },
    {
      "de": "die Entscheidungsarchitektur",
      "en": "choice architecture",
      "example": "Entscheidungsarchitektur gestaltet Optionen bewusst."
    },
    {
      "de": "das begrenzt rationale Verhalten",
      "en": "bounded rational behavior",
      "example": "Begrenzt rationales Verhalten prägt reale Märkte."
    },
    {
      "de": "die Präferenzumkehr",
      "en": "preference reversal",
      "artikel": "die",
      "example": "Präferenzumkehr zeigt inkonsistente Entscheidungen."
    },
    {
      "de": "die Selbstbindung (Ökonomie)",
      "en": "self-commitment (economics)",
      "artikel": "die",
      "example": "Selbstbindung hilft, langfristige Ziele zu erreichen."
    },
    {
      "de": "die Verhaltensmuster analysieren",
      "en": "to analyze behavioral patterns",
      "example": "Ökonomen analysieren Verhaltensmuster von Konsumenten."
    },
    {
      "de": "das ökonomische Experiment",
      "en": "economic experiment",
      "artikel": "das",
      "example": "Das ökonomische Experiment zeigte überraschende Ergebnisse."
    },
    {
      "de": "die Rationalitätsannahme",
      "en": "rationality assumption",
      "artikel": "die",
      "example": "Die klassische Rationalitätsannahme wird oft kritisiert."
    },
    {
      "de": "die Entscheidungsfreiheit einschränken",
      "en": "to restrict freedom of choice",
      "example": "Manche Maßnahmen schränken die Entscheidungsfreiheit ein."
    }
  ]
}