{
  "day": 135,
  "topic": "Bildungsreformen",
  "words": [
    {
      "de": "die Bildungsreform",
      "en": "education reform",
      "artikel": "die",
      "example": "Die Bildungsreform betrifft alle Schulen."
    },
    {
      "de": "das Schulsystem reformieren",
      "en": "to reform the school system",
      "example": "Viele fordern, das Schulsystem zu reformieren."
    },
    {
      "de": "die Ganztagsschule",
      "en": "full-day school",
      "artikel": "die",
      "example": "Die Ganztagsschule wird immer beliebter."
    },
    {
      "de": "die individuelle Förderung",
      "en": "individual support / tutoring",
      "artikel": "die",
      "example": "Individuelle Förderung hilft schwächeren Schülern."
    },
    {
      "de": "die Digitalisierung der Schulen",
      "en": "digitalization of schools",
      "artikel": "die",
      "example": "Die Digitalisierung der Schulen macht Fortschritte."
    },
    {
      "de": "der Lehrermangel",
      "en": "teacher shortage",
      "artikel": "der",
      "example": "Der Lehrermangel betrifft viele Regionen."
    },
    {
      "de": "die Klassengröße",
      "en": "class size",
      "artikel": "die",
      "example": "Die Klassengröße hat großen Einfluss auf das Lernen."
    },
    {
      "de": "inklusiver Unterricht",
      "en": "inclusive teaching",
      "artikel": "der",
      "example": "Inklusiver Unterricht integriert alle Kinder."
    },
    {
      "de": "die Chancengerechtigkeit",
      "en": "equity of opportunity",
      "artikel": "die",
      "example": "Chancengerechtigkeit ist ein zentrales Bildungsziel."
    },
    {
      "de": "die Bildungsungleichheit",
      "en": "educational inequality",
      "artikel": "die",
      "example": "Bildungsungleichheit bleibt ein großes Problem."
    },
    {
      "de": "die Lehrmethode",
      "en": "teaching method",
      "artikel": "die",
      "example": "Neue Lehrmethoden fördern selbstständiges Lernen."
    },
    {
      "de": "projektbasiertes Lernen",
      "en": "project-based learning",
      "example": "Projektbasiertes Lernen motiviert die Schüler."
    },
    {
      "de": "die Prüfungskultur",
      "en": "exam culture",
      "artikel": "die",
      "example": "Die Prüfungskultur wird oft kritisiert."
    },
    {
      "de": "die Notenskala",
      "en": "grading scale",
      "artikel": "die",
      "example": "Die Notenskala unterscheidet sich international."
    },
    {
      "de": "die Schulpflicht",
      "en": "compulsory education",
      "artikel": "die",
      "example": "In Deutschland gilt die Schulpflicht."
    },
    {
      "de": "das lebenslange Lernen fördern",
      "en": "to promote lifelong learning",
      "example": "Wir müssen lebenslanges Lernen fördern."
    },
    {
      "de": "die Berufsorientierung",
      "en": "career orientation",
      "artikel": "die",
      "example": "Berufsorientierung hilft bei der Studienwahl."
    },
    {
      "de": "die MINT-Fächer",
      "en": "STEM subjects",
      "artikel": "die",
      "example": "MINT-Fächer werden stark gefördert."
    },
    {
      "de": "die Fördermaßnahme",
      "en": "support measure",
      "artikel": "die",
      "example": "Diese Fördermaßnahme hilft schwachen Schülern."
    },
    {
      "de": "das Bildungsniveau anheben",
      "en": "to raise the education level",
      "example": "Wir wollen das Bildungsniveau anheben."
    }
  ]
}