{
  "day": 162,
  "topic": "Deutsche Geschichte: Grundzüge",
  "words": [
    {
      "de": "das Heilige Römische Reich",
      "en": "the Holy Roman Empire",
      "example": "Das Heilige Römische Reich bestand über 800 Jahre."
    },
    {
      "de": "die Reformation",
      "en": "the Reformation",
      "artikel": "die",
      "example": "Die Reformation veränderte die Kirche grundlegend."
    },
    {
      "de": "das Kaiserreich",
      "en": "the empire (German)",
      "artikel": "das",
      "example": "Das Kaiserreich wurde 1871 gegründet."
    },
    {
      "de": "die Weimarer Republik",
      "en": "Weimar Republic",
      "artikel": "die",
      "example": "Die Weimarer Republik war Deutschlands erste Demokratie."
    },
    {
      "de": "der Nationalsozialismus",
      "en": "National Socialism",
      "artikel": "der",
      "example": "Der Nationalsozialismus führte zu großem Leid."
    },
    {
      "de": "die Diktatur",
      "en": "dictatorship",
      "artikel": "die",
      "example": "Eine Diktatur unterdrückt Meinungsfreiheit."
    },
    {
      "de": "der Widerstand (Geschichte)",
      "en": "resistance (history)",
      "artikel": "der",
      "example": "Der Widerstand gegen das Regime war gefährlich."
    },
    {
      "de": "die Besatzungszone",
      "en": "occupation zone",
      "artikel": "die",
      "example": "Deutschland wurde in vier Besatzungszonen geteilt."
    },
    {
      "de": "die DDR",
      "en": "the GDR (East Germany)",
      "example": "Die DDR existierte von 1949 bis 1990."
    },
    {
      "de": "die Bundesrepublik",
      "en": "the Federal Republic (West Germany)",
      "artikel": "die",
      "example": "Die Bundesrepublik wurde 1949 gegründet."
    },
    {
      "de": "die Deutsche Einheit",
      "en": "German unity",
      "artikel": "die",
      "example": "Die Deutsche Einheit wird jährlich am 3. Oktober gefeiert."
    },
    {
      "de": "die Verfassung (Deutschland)",
      "en": "constitution (Germany)",
      "artikel": "die",
      "example": "Das Grundgesetz ist die deutsche Verfassung."
    },
    {
      "de": "das Grundgesetz",
      "en": "Basic Law (German constitution)",
      "artikel": "das",
      "example": "Das Grundgesetz schützt die Grundrechte."
    },
    {
      "de": "die föderale Struktur",
      "en": "federal structure",
      "artikel": "die",
      "example": "Deutschland hat eine föderale Struktur."
    },
    {
      "de": "das Bundesland",
      "en": "federal state",
      "artikel": "das",
      "example": "Deutschland hat sechzehn Bundesländer."
    },
    {
      "de": "die Nachkriegsordnung",
      "en": "post-war order",
      "artikel": "die",
      "example": "Die Nachkriegsordnung prägte Europa lange."
    },
    {
      "de": "die Erinnerungsstätte",
      "en": "memorial site",
      "artikel": "die",
      "example": "Die Erinnerungsstätte erinnert an die Opfer."
    },
    {
      "de": "die Gedenkstätte",
      "en": "memorial",
      "artikel": "die",
      "example": "Die Gedenkstätte wird von vielen Schulklassen besucht."
    },
    {
      "de": "die historische Aufarbeitung",
      "en": "historical reappraisal",
      "artikel": "die",
      "example": "Die historische Aufarbeitung ist bis heute wichtig."
    },
    {
      "de": "das Geschichtsbewusstsein",
      "en": "historical awareness",
      "artikel": "das",
      "example": "Geschichtsbewusstsein wird in der Schule vermittelt."
    }
  ]
}